{"code":"SUCCESS","message":"Call API /exchange-index/VNSI?hasHistory=true successful","data":{"exchange":"hose","indexId":"VNSI","indexValue":2163.74,"prevIndexValue":2148.94,"time":1727276523552,"latestValue":[],"advances":14,"allQty":150567320,"allValue":5413699000000,"ceiling":0,"chartHigh":2164.48,"chartLow":2148.94,"declines":5,"floor":0,"nochanges":1,"timeMaker":1727251289944,"totalQtty":137186300,"totalValue":4877119000000,"chartOpen":2157.26,"change":14.8,"changePercent":0.69,"history":[{"indexId":"VNSI","indexValue":2157.26,"time":1727255702801,"vol":1710400,"totalQtty":1710400},{"indexId":"VNSI","indexValue":2158.04,"time":1727255767639,"vol":792000,"totalQtty":2502400},{"indexId":"VNSI","indexValue":2159.37,"time":1727255832637,"vol":559600,"totalQtty":3062000},{"indexId":"VNSI","indexValue":2158.13,"time":1727255897563,"vol":519800,"totalQtty":3581800},{"indexId":"VNSI","indexValue":2157.26,"time":1727255957982,"vol":448800,"totalQtty":4030600},{"indexId":"VNSI","indexValue":2157.8,"time":1727256022656,"vol":339000,"totalQtty":4369600},{"indexId":"VNSI","indexValue":2156.19,"time":1727256087676,"vol":476200,"totalQtty":4845800},{"indexId":"VNSI","indexValue":2155.84,"time":1727256152696,"vol":297400,"totalQtty":5143200},{"indexId":"VNSI","indexValue":2155.86,"time":1727256217487,"vol":229700,"totalQtty":5372900},{"indexId":"VNSI","indexValue":2154.1,"time":1727256282991,"vol":461000,"totalQtty":5833900},{"indexId":"VNSI","indexValue":2153.45,"time":1727256347523,"vol":270700,"totalQtty":6104600},{"indexId":"VNSI","indexValue":2154.12,"time":1727256412642,"vol":232700,"totalQtty":6337300},{"indexId":"VNSI","indexValue":2154.16,"time":1727256472689,"vol":184300,"totalQtty":6521600},{"indexId":"VNSI","indexValue":2153.55,"time":1727256537851,"vol":187300,"totalQtty":6708900},{"indexId":"VNSI","indexValue":2153.21,"time":1727256597891,"vol":398900,"totalQtty":7107800},{"indexId":"VNSI","indexValue":2153.85,"time":1727256657010,"vol":625600,"totalQtty":7733400},{"indexId":"VNSI","indexValue":2153.06,"time":1727256722014,"vol":402400,"totalQtty":8135800},{"indexId":"VNSI","indexValue":2153.06,"time":1727256782151,"vol":240300,"totalQtty":8376100},{"indexId":"VNSI","indexValue":2153.81,"time":1727256847137,"vol":154200,"totalQtty":8530300},{"indexId":"VNSI","indexValue":2153.4,"time":1727256912745,"vol":378200,"totalQtty":8908500},{"indexId":"VNSI","indexValue":2152.54,"time":1727256972918,"vol":176700,"totalQtty":9085200},{"indexId":"VNSI","indexValue":2152.71,"time":1727257037940,"vol":324000,"totalQtty":9409200},{"indexId":"VNSI","indexValue":2152.86,"time":1727257102857,"vol":176200,"totalQtty":9585400},{"indexId":"VNSI","indexValue":2151.87,"time":1727257162358,"vol":555000,"totalQtty":10140400},{"indexId":"VNSI","indexValue":2152.15,"time":1727257227903,"vol":227800,"totalQtty":10368200},{"indexId":"VNSI","indexValue":2152.73,"time":1727257292069,"vol":411900,"totalQtty":10780100},{"indexId":"VNSI","indexValue":2152.45,"time":1727257352163,"vol":446900,"totalQtty":11227000},{"indexId":"VNSI","indexValue":2152.78,"time":1727257412336,"vol":504500,"totalQtty":11731500},{"indexId":"VNSI","indexValue":2152.55,"time":1727257477173,"vol":229400,"totalQtty":11960900},{"indexId":"VNSI","indexValue":2151.78,"time":1727257537401,"vol":209300,"totalQtty":12170200},{"indexId":"VNSI","indexValue":2152.15,"time":1727257602209,"vol":160300,"totalQtty":12330500},{"indexId":"VNSI","indexValue":2152.85,"time":1727257667266,"vol":1393700,"totalQtty":13724200},{"indexId":"VNSI","indexValue":2154.01,"time":1727257732167,"vol":1142400,"totalQtty":14866600},{"indexId":"VNSI","indexValue":2154.11,"time":1727257792570,"vol":1128800,"totalQtty":15995400},{"indexId":"VNSI","indexValue":2154.9,"time":1727257857667,"vol":1681200,"totalQtty":17676600},{"indexId":"VNSI","indexValue":2156.27,"time":1727257917319,"vol":1692000,"totalQtty":19368600},{"indexId":"VNSI","indexValue":2156.84,"time":1727257982209,"vol":1369500,"totalQtty":20738100},{"indexId":"VNSI","indexValue":2156.2,"time":1727258042440,"vol":1080200,"totalQtty":21818300},{"indexId":"VNSI","indexValue":2156.22,"time":1727258107817,"vol":894600,"totalQtty":22712900},{"indexId":"VNSI","indexValue":2156.7,"time":1727258168596,"vol":581900,"totalQtty":23294800},{"indexId":"VNSI","indexValue":2157.72,"time":1727258233457,"vol":436500,"totalQtty":23731300},{"indexId":"VNSI","indexValue":2157.8,"time":1727258298330,"vol":968800,"totalQtty":24700100},{"indexId":"VNSI","indexValue":2157.69,"time":1727258358729,"vol":687700,"totalQtty":25387800},{"indexId":"VNSI","indexValue":2158.33,"time":1727258403289,"vol":348700,"totalQtty":25736500},{"indexId":"VNSI","indexValue":2157.07,"time":1727258608076,"vol":2569300,"totalQtty":28305800},{"indexId":"VNSI","indexValue":2157.22,"time":1727258668468,"vol":454800,"totalQtty":28760600},{"indexId":"VNSI","indexValue":2156.74,"time":1727258728502,"vol":432100,"totalQtty":29192700},{"indexId":"VNSI","indexValue":2155.72,"time":1727258793119,"vol":581000,"totalQtty":29773700},{"indexId":"VNSI","indexValue":2154.45,"time":1727258853016,"vol":682300,"totalQtty":30456000},{"indexId":"VNSI","indexValue":2153.89,"time":1727258918926,"vol":1550600,"totalQtty":32006600},{"indexId":"VNSI","indexValue":2153.18,"time":1727258983528,"vol":1181900,"totalQtty":33188500},{"indexId":"VNSI","indexValue":2153.58,"time":1727259048066,"vol":872300,"totalQtty":34060800},{"indexId":"VNSI","indexValue":2153.99,"time":1727259113774,"vol":539600,"totalQtty":34600400},{"indexId":"VNSI","indexValue":2154.48,"time":1727259178994,"vol":490200,"totalQtty":35090600},{"indexId":"VNSI","indexValue":2153.59,"time":1727259243685,"vol":431600,"totalQtty":35522200},{"indexId":"VNSI","indexValue":2154.37,"time":1727259308626,"vol":654100,"totalQtty":36176300},{"indexId":"VNSI","indexValue":2153.34,"time":1727259373773,"vol":359700,"totalQtty":36536000},{"indexId":"VNSI","indexValue":2153.76,"time":1727259438707,"vol":1123600,"totalQtty":37659600},{"indexId":"VNSI","indexValue":2152.66,"time":1727259503756,"vol":226700,"totalQtty":37886300},{"indexId":"VNSI","indexValue":2152.4,"time":1727259568841,"vol":255700,"totalQtty":38142000},{"indexId":"VNSI","indexValue":2153.35,"time":1727259628852,"vol":223500,"totalQtty":38365500},{"indexId":"VNSI","indexValue":2153.31,"time":1727259693952,"vol":206700,"totalQtty":38572200},{"indexId":"VNSI","indexValue":2154.47,"time":1727259758721,"vol":661300,"totalQtty":39233500},{"indexId":"VNSI","indexValue":2153.41,"time":1727259818141,"vol":1081400,"totalQtty":40314900},{"indexId":"VNSI","indexValue":2153.33,"time":1727259883933,"vol":241100,"totalQtty":40556000},{"indexId":"VNSI","indexValue":2154.07,"time":1727259948357,"vol":564200,"totalQtty":41120200},{"indexId":"VNSI","indexValue":2154.47,"time":1727260008873,"vol":442000,"totalQtty":41562200},{"indexId":"VNSI","indexValue":2154.48,"time":1727260068233,"vol":370600,"totalQtty":41932800},{"indexId":"VNSI","indexValue":2154.5,"time":1727260133202,"vol":204700,"totalQtty":42137500},{"indexId":"VNSI","indexValue":2155.06,"time":1727260193565,"vol":986800,"totalQtty":43124300},{"indexId":"VNSI","indexValue":2155.55,"time":1727260258381,"vol":434200,"totalQtty":43558500},{"indexId":"VNSI","indexValue":2155.94,"time":1727260323287,"vol":327300,"totalQtty":43885800},{"indexId":"VNSI","indexValue":2155.56,"time":1727260383537,"vol":310600,"totalQtty":44196400},{"indexId":"VNSI","indexValue":2155.44,"time":1727260448488,"vol":291100,"totalQtty":44487500},{"indexId":"VNSI","indexValue":2156.22,"time":1727260513328,"vol":674000,"totalQtty":45161500},{"indexId":"VNSI","indexValue":2154.77,"time":1727260578013,"vol":740300,"totalQtty":45901800},{"indexId":"VNSI","indexValue":2154.12,"time":1727260643116,"vol":1412900,"totalQtty":47314700},{"indexId":"VNSI","indexValue":2154.33,"time":1727260703608,"vol":419300,"totalQtty":47734000},{"indexId":"VNSI","indexValue":2154.7,"time":1727260768481,"vol":765900,"totalQtty":48499900},{"indexId":"VNSI","indexValue":2155.94,"time":1727260833537,"vol":541500,"totalQtty":49041400},{"indexId":"VNSI","indexValue":2156.07,"time":1727260899165,"vol":494200,"totalQtty":49535600},{"indexId":"VNSI","indexValue":2156.35,"time":1727260959670,"vol":892000,"totalQtty":50427600},{"indexId":"VNSI","indexValue":2156.99,"time":1727261024758,"vol":851800,"totalQtty":51279400},{"indexId":"VNSI","indexValue":2157.06,"time":1727261084791,"vol":551500,"totalQtty":51830900},{"indexId":"VNSI","indexValue":2157.28,"time":1727261149946,"vol":506800,"totalQtty":52337700},{"indexId":"VNSI","indexValue":2158.14,"time":1727261214171,"vol":264100,"totalQtty":52601800},{"indexId":"VNSI","indexValue":2157.18,"time":1727261274625,"vol":445100,"totalQtty":53046900},{"indexId":"VNSI","indexValue":2156.8,"time":1727261339731,"vol":721800,"totalQtty":53768700},{"indexId":"VNSI","indexValue":2155.78,"time":1727261399815,"vol":270400,"totalQtty":54039100},{"indexId":"VNSI","indexValue":2157.51,"time":1727261464588,"vol":287100,"totalQtty":54326200},{"indexId":"VNSI","indexValue":2158.44,"time":1727261529461,"vol":304300,"totalQtty":54630500},{"indexId":"VNSI","indexValue":2158.55,"time":1727261594641,"vol":297700,"totalQtty":54928200},{"indexId":"VNSI","indexValue":2159.88,"time":1727261659692,"vol":304700,"totalQtty":55232900},{"indexId":"VNSI","indexValue":2159.96,"time":1727261724873,"vol":544300,"totalQtty":55777200},{"indexId":"VNSI","indexValue":2159.47,"time":1727261789983,"vol":412000,"totalQtty":56189200},{"indexId":"VNSI","indexValue":2158.89,"time":1727261854166,"vol":200500,"totalQtty":56389700},{"indexId":"VNSI","indexValue":2159.29,"time":1727261919351,"vol":603100,"totalQtty":56992800},{"indexId":"VNSI","indexValue":2159.19,"time":1727261984736,"vol":317800,"totalQtty":57310600},{"indexId":"VNSI","indexValue":2160.39,"time":1727262044988,"vol":190100,"totalQtty":57500700},{"indexId":"VNSI","indexValue":2160.5,"time":1727262109951,"vol":461700,"totalQtty":57962400},{"indexId":"VNSI","indexValue":2159.69,"time":1727262169002,"vol":913300,"totalQtty":58875700},{"indexId":"VNSI","indexValue":2159.7,"time":1727262234129,"vol":369300,"totalQtty":59245000},{"indexId":"VNSI","indexValue":2160.35,"time":1727262294260,"vol":525800,"totalQtty":59770800},{"indexId":"VNSI","indexValue":2159.58,"time":1727262359435,"vol":435200,"totalQtty":60206000},{"indexId":"VNSI","indexValue":2160.03,"time":1727262419542,"vol":242800,"totalQtty":60448800},{"indexId":"VNSI","indexValue":2159.4,"time":1727262479867,"vol":464000,"totalQtty":60912800},{"indexId":"VNSI","indexValue":2161.15,"time":1727262539957,"vol":1088600,"totalQtty":62001400},{"indexId":"VNSI","indexValue":2161.09,"time":1727262599099,"vol":739300,"totalQtty":62740700},{"indexId":"VNSI","indexValue":2161.05,"time":1727262664195,"vol":1177000,"totalQtty":63917700},{"indexId":"VNSI","indexValue":2161.43,"time":1727262724311,"vol":1032000,"totalQtty":64949700},{"indexId":"VNSI","indexValue":2161.17,"time":1727262789068,"vol":1862000,"totalQtty":66811700},{"indexId":"VNSI","indexValue":2162.08,"time":1727262854932,"vol":1594000,"totalQtty":68405700},{"indexId":"VNSI","indexValue":2162.74,"time":1727262914189,"vol":1452200,"totalQtty":69857900},{"indexId":"VNSI","indexValue":2163.72,"time":1727262974449,"vol":1682100,"totalQtty":71540000},{"indexId":"VNSI","indexValue":2163.74,"time":1727263034638,"vol":949000,"totalQtty":72489000},{"indexId":"VNSI","indexValue":2163.78,"time":1727263099238,"vol":509600,"totalQtty":72998600},{"indexId":"VNSI","indexValue":2163.62,"time":1727263159433,"vol":554100,"totalQtty":73552700},{"indexId":"VNSI","indexValue":2163.04,"time":1727263224111,"vol":471700,"totalQtty":74024400},{"indexId":"VNSI","indexValue":2162.61,"time":1727263284240,"vol":251000,"totalQtty":74275400},{"indexId":"VNSI","indexValue":2162.78,"time":1727263344371,"vol":168900,"totalQtty":74444300},{"indexId":"VNSI","indexValue":2162.68,"time":1727263409597,"vol":573400,"totalQtty":75017700},{"indexId":"VNSI","indexValue":2161.97,"time":1727263469602,"vol":530200,"totalQtty":75547900},{"indexId":"VNSI","indexValue":2162.34,"time":1727263530652,"vol":145400,"totalQtty":75693300},{"indexId":"VNSI","indexValue":2162.24,"time":1727263590659,"vol":478500,"totalQtty":76171800},{"indexId":"VNSI","indexValue":2162.02,"time":1727263655888,"vol":405000,"totalQtty":76576800},{"indexId":"VNSI","indexValue":2162,"time":1727263715697,"vol":315600,"totalQtty":76892400},{"indexId":"VNSI","indexValue":2162.61,"time":1727263780757,"vol":626100,"totalQtty":77518500},{"indexId":"VNSI","indexValue":2162.05,"time":1727263845831,"vol":84200,"totalQtty":77602700},{"indexId":"VNSI","indexValue":2162.05,"time":1727263910527,"vol":0,"totalQtty":77602700},{"indexId":"VNSI","indexValue":2162.52,"time":1727269205513,"vol":597700,"totalQtty":78200400},{"indexId":"VNSI","indexValue":2162.68,"time":1727269270001,"vol":650400,"totalQtty":78850800},{"indexId":"VNSI","indexValue":2161.74,"time":1727269330433,"vol":360400,"totalQtty":79211200},{"indexId":"VNSI","indexValue":2162.31,"time":1727269395363,"vol":785800,"totalQtty":79997000},{"indexId":"VNSI","indexValue":2162.93,"time":1727269455469,"vol":257800,"totalQtty":80254800},{"indexId":"VNSI","indexValue":2163.02,"time":1727269520923,"vol":519200,"totalQtty":80774000},{"indexId":"VNSI","indexValue":2163.06,"time":1727269580039,"vol":448600,"totalQtty":81222600},{"indexId":"VNSI","indexValue":2161.76,"time":1727269645558,"vol":365300,"totalQtty":81587900},{"indexId":"VNSI","indexValue":2162.21,"time":1727269705315,"vol":237600,"totalQtty":81825500},{"indexId":"VNSI","indexValue":2162.39,"time":1727269765487,"vol":1105800,"totalQtty":82931300},{"indexId":"VNSI","indexValue":2162.35,"time":1727269830116,"vol":423800,"totalQtty":83355100},{"indexId":"VNSI","indexValue":2162.77,"time":1727269890448,"vol":476500,"totalQtty":83831600},{"indexId":"VNSI","indexValue":2162.74,"time":1727269955355,"vol":576700,"totalQtty":84408300},{"indexId":"VNSI","indexValue":2161.28,"time":1727270015664,"vol":224600,"totalQtty":84632900},{"indexId":"VNSI","indexValue":2160.97,"time":1727270080384,"vol":612300,"totalQtty":85245200},{"indexId":"VNSI","indexValue":2161.3,"time":1727270140590,"vol":325800,"totalQtty":85571000},{"indexId":"VNSI","indexValue":2161.65,"time":1727270205288,"vol":310000,"totalQtty":85881000},{"indexId":"VNSI","indexValue":2161.35,"time":1727270266736,"vol":309200,"totalQtty":86190200},{"indexId":"VNSI","indexValue":2161.77,"time":1727270331988,"vol":990400,"totalQtty":87180600},{"indexId":"VNSI","indexValue":2162,"time":1727270391550,"vol":1319500,"totalQtty":88500100},{"indexId":"VNSI","indexValue":2161.61,"time":1727270456670,"vol":308900,"totalQtty":88809000},{"indexId":"VNSI","indexValue":2161.45,"time":1727270521585,"vol":977400,"totalQtty":89786400},{"indexId":"VNSI","indexValue":2161.83,"time":1727270586442,"vol":622400,"totalQtty":90408800},{"indexId":"VNSI","indexValue":2161.3,"time":1727270651580,"vol":380800,"totalQtty":90789600},{"indexId":"VNSI","indexValue":2162.83,"time":1727270716720,"vol":580600,"totalQtty":91370200},{"indexId":"VNSI","indexValue":2160.49,"time":1727270781545,"vol":577300,"totalQtty":91947500},{"indexId":"VNSI","indexValue":2161.45,"time":1727270846653,"vol":426100,"totalQtty":92373600},{"indexId":"VNSI","indexValue":2162.29,"time":1727270906984,"vol":358800,"totalQtty":92732400},{"indexId":"VNSI","indexValue":2162.57,"time":1727270971716,"vol":413300,"totalQtty":93145700},{"indexId":"VNSI","indexValue":2161.67,"time":1727271036601,"vol":301200,"totalQtty":93446900},{"indexId":"VNSI","indexValue":2161.47,"time":1727271096758,"vol":316400,"totalQtty":93763300},{"indexId":"VNSI","indexValue":2161.35,"time":1727271156978,"vol":548700,"totalQtty":94312000},{"indexId":"VNSI","indexValue":2160.5,"time":1727271221599,"vol":624400,"totalQtty":94936400},{"indexId":"VNSI","indexValue":2160.82,"time":1727271281848,"vol":917100,"totalQtty":95853500},{"indexId":"VNSI","indexValue":2161.11,"time":1727271346825,"vol":392700,"totalQtty":96246200},{"indexId":"VNSI","indexValue":2160.42,"time":1727271406159,"vol":381800,"totalQtty":96628000},{"indexId":"VNSI","indexValue":2160.87,"time":1727271471923,"vol":587400,"totalQtty":97215400},{"indexId":"VNSI","indexValue":2159.87,"time":1727271531025,"vol":285300,"totalQtty":97500700},{"indexId":"VNSI","indexValue":2160.31,"time":1727271596866,"vol":747200,"totalQtty":98247900},{"indexId":"VNSI","indexValue":2160.78,"time":1727271656121,"vol":649400,"totalQtty":98897300},{"indexId":"VNSI","indexValue":2160,"time":1727271721039,"vol":803900,"totalQtty":99701200},{"indexId":"VNSI","indexValue":2160.44,"time":1727271781150,"vol":474000,"totalQtty":100175200},{"indexId":"VNSI","indexValue":2161.23,"time":1727271846840,"vol":533800,"totalQtty":100709000},{"indexId":"VNSI","indexValue":2159.56,"time":1727271906287,"vol":477300,"totalQtty":101186300},{"indexId":"VNSI","indexValue":2159.34,"time":1727271971055,"vol":531900,"totalQtty":101718200},{"indexId":"VNSI","indexValue":2159.28,"time":1727272036991,"vol":567900,"totalQtty":102286100},{"indexId":"VNSI","indexValue":2158.59,"time":1727272096405,"vol":389600,"totalQtty":102675700},{"indexId":"VNSI","indexValue":2158.92,"time":1727272161204,"vol":584800,"totalQtty":103260500},{"indexId":"VNSI","indexValue":2158.59,"time":1727272226201,"vol":377800,"totalQtty":103638300},{"indexId":"VNSI","indexValue":2159.16,"time":1727272286396,"vol":667600,"totalQtty":104305900},{"indexId":"VNSI","indexValue":2160.22,"time":1727272351060,"vol":438300,"totalQtty":104744200},{"indexId":"VNSI","indexValue":2159.67,"time":1727272411073,"vol":1040900,"totalQtty":105785100},{"indexId":"VNSI","indexValue":2160.82,"time":1727272476088,"vol":1626200,"totalQtty":107411300},{"indexId":"VNSI","indexValue":2160.65,"time":1727272536473,"vol":495500,"totalQtty":107906800},{"indexId":"VNSI","indexValue":2161.11,"time":1727272601335,"vol":379900,"totalQtty":108286700},{"indexId":"VNSI","indexValue":2161.46,"time":1727272666118,"vol":795500,"totalQtty":109082200},{"indexId":"VNSI","indexValue":2160.1,"time":1727272726228,"vol":1272200,"totalQtty":110354400},{"indexId":"VNSI","indexValue":2160.8,"time":1727272786675,"vol":682700,"totalQtty":111037100},{"indexId":"VNSI","indexValue":2161.76,"time":1727272851475,"vol":574600,"totalQtty":111611700},{"indexId":"VNSI","indexValue":2161.94,"time":1727272912624,"vol":361100,"totalQtty":111972800},{"indexId":"VNSI","indexValue":2161.71,"time":1727272977402,"vol":335300,"totalQtty":112308100},{"indexId":"VNSI","indexValue":2162.14,"time":1727273037701,"vol":495100,"totalQtty":112803200},{"indexId":"VNSI","indexValue":2160.91,"time":1727273102659,"vol":588600,"totalQtty":113391800},{"indexId":"VNSI","indexValue":2160.6,"time":1727273167328,"vol":380600,"totalQtty":113772400},{"indexId":"VNSI","indexValue":2162.11,"time":1727273227449,"vol":903000,"totalQtty":114675400},{"indexId":"VNSI","indexValue":2160.92,"time":1727273292539,"vol":582400,"totalQtty":115257800},{"indexId":"VNSI","indexValue":2160.72,"time":1727273352857,"vol":387000,"totalQtty":115644800},{"indexId":"VNSI","indexValue":2159.95,"time":1727273417301,"vol":582800,"totalQtty":116227600},{"indexId":"VNSI","indexValue":2160.08,"time":1727273477808,"vol":758100,"totalQtty":116985700},{"indexId":"VNSI","indexValue":2161.58,"time":1727273542817,"vol":332800,"totalQtty":117318500},{"indexId":"VNSI","indexValue":2160.55,"time":1727273607891,"vol":524800,"totalQtty":117843300},{"indexId":"VNSI","indexValue":2160.28,"time":1727273672107,"vol":456300,"totalQtty":118299600},{"indexId":"VNSI","indexValue":2159.91,"time":1727273732775,"vol":355300,"totalQtty":118654900},{"indexId":"VNSI","indexValue":2160.02,"time":1727273792844,"vol":304400,"totalQtty":118959300},{"indexId":"VNSI","indexValue":2160.07,"time":1727273852042,"vol":531500,"totalQtty":119490800},{"indexId":"VNSI","indexValue":2159.38,"time":1727273917678,"vol":700400,"totalQtty":120191200},{"indexId":"VNSI","indexValue":2160.5,"time":1727273982711,"vol":448600,"totalQtty":120639800},{"indexId":"VNSI","indexValue":2160.04,"time":1727274047631,"vol":1061200,"totalQtty":121701000},{"indexId":"VNSI","indexValue":2160.01,"time":1727274107077,"vol":691400,"totalQtty":122392400},{"indexId":"VNSI","indexValue":2160.84,"time":1727274172208,"vol":1064000,"totalQtty":123456400},{"indexId":"VNSI","indexValue":2159.97,"time":1727274237167,"vol":765600,"totalQtty":124222000},{"indexId":"VNSI","indexValue":2160.31,"time":1727274302938,"vol":835900,"totalQtty":125057900},{"indexId":"VNSI","indexValue":2159.99,"time":1727274362026,"vol":1280900,"totalQtty":126338800},{"indexId":"VNSI","indexValue":2161.49,"time":1727274427882,"vol":1100100,"totalQtty":127438900},{"indexId":"VNSI","indexValue":2162.59,"time":1727274492078,"vol":1033800,"totalQtty":128472700},{"indexId":"VNSI","indexValue":2162.36,"time":1727274557153,"vol":1078900,"totalQtty":129551600},{"indexId":"VNSI","indexValue":2163.74,"time":1727275503031,"vol":7634700,"totalQtty":137186300},{"indexId":"VNSI","indexValue":2163.74,"time":1727275588686,"vol":0,"totalQtty":137186300},{"indexId":"VNSI","indexValue":2163.74,"time":1727275653659,"vol":0,"totalQtty":137186300},{"indexId":"VNSI","indexValue":2163.74,"time":1727275718702,"vol":0,"totalQtty":137186300},{"indexId":"VNSI","indexValue":2163.74,"time":1727275783278,"vol":0,"totalQtty":137186300},{"indexId":"VNSI","indexValue":2163.74,"time":1727275848404,"vol":0,"totalQtty":137186300},{"indexId":"VNSI","indexValue":2163.74,"time":1727275913631,"vol":0,"totalQtty":137186300},{"indexId":"VNSI","indexValue":2163.74,"time":1727275978669,"vol":0,"totalQtty":137186300},{"indexId":"VNSI","indexValue":2163.74,"time":1727276043126,"vol":0,"totalQtty":137186300},{"indexId":"VNSI","indexValue":2163.74,"time":1727276108458,"vol":0,"totalQtty":137186300},{"indexId":"VNSI","indexValue":2163.74,"time":1727276168070,"vol":0,"totalQtty":137186300},{"indexId":"VNSI","indexValue":2163.74,"time":1727276233175,"vol":0,"totalQtty":137186300},{"indexId":"VNSI","indexValue":2163.74,"time":1727276293739,"vol":0,"totalQtty":137186300},{"indexId":"VNSI","indexValue":2163.74,"time":1727276358848,"vol":0,"totalQtty":137186300},{"indexId":"VNSI","indexValue":2163.74,"time":1727276423934,"vol":0,"totalQtty":137186300},{"indexId":"VNSI","indexValue":2163.74,"time":1727276488944,"vol":0,"totalQtty":137186300}],"totalBuyForeignQtty":80428235,"totalSellForeignQtty":60032160,"label":"VNSI","exchangeLabel":"VNSI"}}